boss/__init__.py
boss/__main__.py
boss/keywords.py
boss/settings.py
boss/bo/__init__.py
boss/bo/bo_main.py
boss/bo/convergence.py
boss/bo/factory.py
boss/bo/hmc.py
boss/bo/initmanager.py
boss/bo/results.py
boss/bo/rstmanager.py
boss/bo/userfunc.py
boss/bo/acq/__init__.py
boss/bo/acq/acquisition.py
boss/bo/acq/cost.py
boss/bo/acq/ei.py
boss/bo/acq/elcb.py
boss/bo/acq/exploit.py
boss/bo/acq/explore.py
boss/bo/acq/kb.py
boss/bo/acq/lcb.py
boss/bo/acq/manager.py
boss/bo/acq/mes.py
boss/bo/acq/multi.py
boss/bo/kernels/__init__.py
boss/bo/kernels/kernel_factory.py
boss/bo/kernels/torch/__init__.py
boss/bo/kernels/torch/kernel_factory.py
boss/bo/models/__init__.py
boss/bo/models/gradient.py
boss/bo/models/heteroscedastic.py
boss/bo/models/model.py
boss/bo/models/multi_task.py
boss/bo/models/single_task.py
boss/bo/models/torch/__init__.py
boss/bo/models/torch/single_task.py
boss/io/__init__.py
boss/io/dump.py
boss/io/ioutils.py
boss/io/main_output.py
boss/io/parse.py
boss/mep/__init__.py
boss/mep/forest.py
boss/mep/mep.py
boss/mep/mepmain.py
boss/mep/neb.py
boss/mep/node.py
boss/mep/path.py
boss/mep/space.py
boss/pp/__init__.py
boss/pp/mesh.py
boss/pp/pf_main.py
boss/pp/plot.py
boss/pp/pp_main.py
boss/testing/__init__.py
boss/testing/benchmark.py
boss/testing/db.py
boss/testing/testfunc.py
boss/utils/__init__.py
boss/utils/arrays.py
boss/utils/distributions.py
boss/utils/minimization.py
boss/utils/os.py
boss/utils/sparselist.py
boss/utils/timer.py
aalto_boss-1.13.1.dist-info/LICENSE
aalto_boss-1.13.1.dist-info/METADATA
aalto_boss-1.13.1.dist-info/WHEEL
aalto_boss-1.13.1.dist-info/entry_points.txt
aalto_boss-1.13.1.dist-info/top_level.txt
aalto_boss-1.13.1.dist-info/RECORD
