Metadata-Version: 2.1
Name: aalto-boss
Version: 1.13.1
Summary: Bayesian optimization structure search
Home-page: https://gitlab.com/cest-group/boss
Author: Yuhao Zhang, Ville Parkkinen, Henri Paulamaki, Arttu Tolvanen, Ulpu Remes, Nuutti Sten, Emma Lehto, Mikael Granit, Manuel Kuchelmeister, Tatu Linnala, Tuomas Rossi, Ransell Dsouza, Matthias Stosiek, Armi Tiihonen, Joakim Loefgren, Milica Todorovic, 
Maintainer: The BOSS developers team
Maintainer-email: milica.todorovic@utu.fi
License: Apache License 2.0
Classifier: Development Status :: 5 - Production/Stable
Classifier: Operating System :: OS Independent
Classifier: Intended Audience :: Science/Research
Classifier: Topic :: Scientific/Engineering :: Artificial Intelligence
Classifier: Topic :: Scientific/Engineering :: Physics
Classifier: Topic :: Scientific/Engineering :: Mathematics
Classifier: Programming Language :: Python
Classifier: Programming Language :: Python :: 3
Classifier: Programming Language :: Python :: 3 :: Only
Classifier: Programming Language :: Python :: 3.10
Classifier: Programming Language :: Python :: 3.11
Classifier: License :: OSI Approved :: Apache Software License
Requires-Python: >=3.10
License-File: LICENSE
Requires-Dist: numpy>=1.20
Requires-Dist: GPy>=1.13.1
Requires-Dist: scipy>=1.8
Requires-Dist: matplotlib<3.9,>=3.5
Provides-Extra: benchmark
Requires-Dist: sqlalchemy; extra == "benchmark"
